irida_staramr_results/__init__.py
irida_staramr_results/cli.py
irida_staramr_results/downloader.py
irida_staramr_results/filter.py
irida_staramr_results/util.py
irida_staramr_results/validate.py
irida_staramr_results/version.py
irida_staramr_results/api/__init__.py
irida_staramr_results/api/irida_api.py
irida_staramr_results/api/exceptions/__init__.py
irida_staramr_results/api/exceptions/irida_connection_error.py
irida_staramr_results/api/exceptions/irida_key_error.py
irida_staramr_results/api/exceptions/irida_resource_error.py
irida_staramr_results/model/__init__.py
irida_staramr_results/model/result.py
irida_staramr_results/parser/__init__.py
irida_staramr_results/parser/parser.py
irida_staramr_results/parser/exceptions/__init__.py
irida_staramr_results/parser/exceptions/config_file_not_found_error.py
irida_staramr_results/parser/exceptions/config_information_error.py
irida_staramr_results/test_unit/__init__.py
irida_staramr_results/test_unit/test_downloader.py
irida_staramr_results/test_unit/test_filter.py
irida_staramr_results/test_unit/test_irida_api.py
irida_staramr_results/test_unit/test_util.py
irida_staramr_results/test_unit/test_validate.py
irida_staramr_results-0.3.1.dist-info/LICENSE
irida_staramr_results-0.3.1.dist-info/METADATA
irida_staramr_results-0.3.1.dist-info/WHEEL
irida_staramr_results-0.3.1.dist-info/entry_points.txt
irida_staramr_results-0.3.1.dist-info/top_level.txt
irida_staramr_results-0.3.1.dist-info/RECORD
