Metadata-Version: 2.1
Name: irida-staramr-results
Version: 0.3.1
Summary: IRIDA StarAMR Results program enables StarAMR analysis results that were run through IRIDA to be batch downloaded into a collection of spreadsheets using the command line.
Home-page: https://github.com/phac-nml/irida-staramr-results
Author: Marielle Manlulu
Author-email: marielle.manlulu@canada.ca
License: Apache-2.0
Platform: UNKNOWN
Classifier: Development Status :: 4 - Beta
Classifier: Environment :: Console
Classifier: Intended Audience :: Science/Research
Classifier: Natural Language :: English
Classifier: Operating System :: POSIX :: Linux
Classifier: Programming Language :: Python :: 3.8
Classifier: Topic :: Scientific/Engineering :: Bio-Informatics
Classifier: License :: OSI Approved :: Apache Software License
Requires-Dist: rauth
Requires-Dist: requests
Requires-Dist: setuptools
Requires-Dist: pyyaml
Requires-Dist: pandas
Requires-Dist: openpyxl
Requires-Dist: xlsxwriter
Requires-Dist: python-dateutil
